better_python_doppler/__init__.py
better_python_doppler/doppler_sdk.py
better_python_doppler/secret.py
better_python_doppler/apis/__init__.py
better_python_doppler/apis/config_apis.py
better_python_doppler/apis/environment_apis.py
better_python_doppler/apis/project_apis.py
better_python_doppler/apis/secret_apis.py
better_python_doppler/models/DEPRECATED - config.py
better_python_doppler/models/DEPRECATED - environment.py
better_python_doppler/models/DEPRECATED - project.py
better_python_doppler/models/__init__.py
better_python_doppler/models/secret.py
better_python_doppler/utilities/__init__.py
better_python_doppler/utilities/utilities.py
better_python_doppler-1.0.0.dist-info/licenses/LICENSE
better_python_doppler-1.0.0.dist-info/METADATA
better_python_doppler-1.0.0.dist-info/WHEEL
better_python_doppler-1.0.0.dist-info/top_level.txt
better_python_doppler-1.0.0.dist-info/RECORD
