Metadata-Version: 2.4
Name: better-python-doppler
Version: 1.0.0
Summary: A simplified and up to date Python SDK for Doppler. Because their current one has stale docs and doesn't provide much IDE support.
Author-email: Derek Banker <dbb2002@gmail.com>
License-Expression: Apache-2.0
Keywords: Doppler,SKD
Classifier: Programming Language :: Python
Requires-Python: >=3.12
License-File: LICENSE
Dynamic: license-file
